pinkrst/__init__.py
pinkrst/pinkrst.py
pinkrst-0.0.1.post2.dist-info/METADATA
pinkrst-0.0.1.post2.dist-info/WHEEL
pinkrst-0.0.1.post2.dist-info/entry_points.txt
pinkrst-0.0.1.post2.dist-info/RECORD
