Metadata-Version: 2.1
Name: pinkrst
Version: 0.0.1.post2
Summary: Opinionated ReStructured Text (.rst) Formatter
Author: Gwyn Uttmark
Author-email: biosafetylevel5@gmail.com
Requires-Python: >=3.6
Classifier: Operating System :: OS Independent
Classifier: Programming Language :: Python :: 3
Classifier: Programming Language :: Python :: 3.6
Classifier: Programming Language :: Python :: 3.7
Classifier: Programming Language :: Python :: 3.8
Classifier: Programming Language :: Python :: 3.9
Classifier: Programming Language :: Python :: 3.10
Classifier: Programming Language :: Python :: 3.11
Classifier: Programming Language :: Python :: 3.12
Provides-Extra: doc
Requires-Dist: rich
Requires-Dist: rich-argparse
Requires-Dist: sphinx ; extra == "doc"
Requires-Dist: sphinxcontrib-napoleon ; extra == "doc"
Requires-Dist: sphinxcontrib-runcmd ; extra == "doc"
Project-URL: Homepage, https://github.com/biosafetylvl5/pinkrst
Project-URL: Issues, https://github.com/biosafetylvl5/pinkrst/issues
